pook/__init__.py
pook/activate_async.py
pook/api.py
pook/assertion.py
pook/compare.py
pook/constants.py
pook/engine.py
pook/exceptions.py
pook/headers.py
pook/helpers.py
pook/matcher.py
pook/mock.py
pook/mock_engine.py
pook/regex.py
pook/request.py
pook/response.py
pook/interceptors/__init__.py
pook/interceptors/aiohttp.py
pook/interceptors/base.py
pook/interceptors/http.py
pook/interceptors/pycurl.py
pook/interceptors/urllib3.py
pook/matchers/__init__.py
pook/matchers/api.py
pook/matchers/base.py
pook/matchers/body.py
pook/matchers/headers.py
pook/matchers/json.py
pook/matchers/json_schema.py
pook/matchers/method.py
pook/matchers/path.py
pook/matchers/query.py
pook/matchers/url.py
pook/matchers/xml.py
tests/integration/__init__.py
tests/integration/engines_test.py
tests/integration/examples_test.py
tests/integration/pook_requests_test.py
tests/integration/engines/__init__.py
tests/integration/engines/nose_suite.py
tests/integration/engines/pytest_suite.py
tests/integration/engines/unittest_suite.py
tests/unit/__init__.py
tests/unit/api_test.py
tests/unit/engine_test.py
tests/unit/exceptions_test.py
tests/unit/matcher_test.py
tests/unit/mock_engine_test.py
tests/unit/mock_test.py
tests/unit/regex_test.py
tests/unit/interceptors/__init__.py
tests/unit/interceptors/module_test.py
tests/unit/interceptors/urllib3_test.py
tests/unit/matchers/__init__.py
tests/unit/matchers/base_test.py
tests/unit/matchers/body_test.py
tests/unit/matchers/headers_test.py
tests/unit/matchers/helpers_test.py
tests/unit/matchers/json_schema_test.py
tests/unit/matchers/json_test.py
tests/unit/matchers/method_test.py
tests/unit/matchers/path_test.py
tests/unit/matchers/query_test.py
tests/unit/matchers/url_test.py
modern_pook-2.0.0.dist-info/LICENSE
modern_pook-2.0.0.dist-info/METADATA
modern_pook-2.0.0.dist-info/WHEEL
modern_pook-2.0.0.dist-info/top_level.txt
modern_pook-2.0.0.dist-info/RECORD
