Metadata-Version: 2.1
Name: modern-pook
Version: 2.0.0
Summary: HTTP traffic mocking and expectations made easy
Home-page: https://github.com/h2non/pook
Author: Tomas Aparicio
Author-email: tomas@aparicio.me
License: MIT
Classifier: Intended Audience :: Developers
Classifier: Intended Audience :: System Administrators
Classifier: Operating System :: OS Independent
Classifier: Development Status :: 5 - Production/Stable
Classifier: Natural Language :: English
Classifier: License :: OSI Approved :: MIT License
Classifier: Programming Language :: Python :: 3
Classifier: Programming Language :: Python :: 3.8
Classifier: Programming Language :: Python :: 3.9
Classifier: Programming Language :: Python :: 3.10
Classifier: Programming Language :: Python :: 3.11
Classifier: Topic :: Software Development
Classifier: Topic :: Software Development :: Libraries :: Python Modules
Classifier: Programming Language :: Python :: Implementation :: CPython
Classifier: Programming Language :: Python :: Implementation :: PyPy
License-File: LICENSE
Requires-Dist: jsonschema (>=2.5.1)
Requires-Dist: xmltodict (>=0.11.0)
Requires-Dist: furl (>=0.5.6)
Requires-Dist: mock (>=2.0.0) ; python_version < "3.3"
